ClassPy/Classpy.py
ClassPy/__init__.py
ClassPy/flagsClass.py
ClassPy/functionsClassPy.py
ClassPy/invokeclass.py
ClassPy/propsClass.py
ClassPy/propsFunction.py
classpy-1.0.1.dist-info/METADATA
classpy-1.0.1.dist-info/WHEEL
classpy-1.0.1.dist-info/top_level.txt
classpy-1.0.1.dist-info/RECORD
